bml_connect/__init__.py
bml_connect/client.py
bml_connect_python-1.1.0.dist-info/licenses/LICENSE
bml_connect_python-1.1.0.dist-info/METADATA
bml_connect_python-1.1.0.dist-info/WHEEL
bml_connect_python-1.1.0.dist-info/top_level.txt
bml_connect_python-1.1.0.dist-info/RECORD
