Metadata-Version: 2.4
Name: bml-connect-python
Version: 1.1.0
Summary: Python SDK for Bank of Maldives Connect API with sync/async support
Author-email: Ali Fayaz <fayaz.quill@gmail.com>
License-Expression: MIT
Project-URL: Homepage, https://github.com/quillfires/bml-connect-python
Project-URL: Repository, https://github.com/quillfires/bml-connect-python
Project-URL: Issues, https://github.com/quillfires/bml-connect-python/issues
Project-URL: Changelog, https://github.com/quillfires/bml-connect-python/releases
Classifier: Development Status :: 5 - Production/Stable
Classifier: Intended Audience :: Developers
Classifier: Operating System :: OS Independent
Classifier: Programming Language :: Python :: 3
Classifier: Programming Language :: Python :: 3.7
Classifier: Programming Language :: Python :: 3.8
Classifier: Programming Language :: Python :: 3.9
Classifier: Programming Language :: Python :: 3.10
Classifier: Programming Language :: Python :: 3.11
Classifier: Programming Language :: Python :: 3.12
Classifier: Topic :: Software Development :: Libraries :: Python Modules
Classifier: Topic :: Office/Business :: Financial :: Point-Of-Sale
Classifier: Topic :: Internet :: WWW/HTTP :: Dynamic Content
Requires-Python: >=3.7
License-File: LICENSE
Requires-Dist: requests>=2.28.0
Requires-Dist: aiohttp>=3.8.0
Provides-Extra: dev
Requires-Dist: pytest>=7.0.0; extra == "dev"
Requires-Dist: pytest-asyncio>=0.20.0; extra == "dev"
Requires-Dist: pytest-cov>=4.0.0; extra == "dev"
Requires-Dist: black>=22.0.0; extra == "dev"
Requires-Dist: flake8>=5.0.0; extra == "dev"
Requires-Dist: mypy>=0.990; extra == "dev"
Requires-Dist: pre-commit>=2.20.0; extra == "dev"
Requires-Dist: types-requests>=2.28.0; extra == "dev"
Provides-Extra: django
Requires-Dist: django>=3.2; extra == "django"
Provides-Extra: flask
Requires-Dist: flask>=2.0; extra == "flask"
Provides-Extra: fastapi
Requires-Dist: fastapi>=0.68.0; extra == "fastapi"
Requires-Dist: uvicorn>=0.15.0; extra == "fastapi"
Provides-Extra: sanic
Requires-Dist: sanic>=22.0.0; extra == "sanic"
Dynamic: license-file
